{
  "comp name": "Majesty Dancesport",
  "heats": [
    {
      "title": "AC-A Open Smooth 3-Dance Challenge (W/T/F)",
      "entries": [
        {
          "couple": "Ward, Janice and Ward, Walter",
          "place": "1",
          "points": 25.0
        },
        {
          "couple": "Bartlett, James and Jane, Catherine",
          "place": "2",
          "points": 20.0
        },
        {
          "couple": "Sutherland and Sutherland",
          "place": "3",
          "points": 16.25
        },
        {
          "couple": "Vangjel, Joanne and Vangjel, Pete",
          "place": "4",
          "points": 12.5
        },
        {
          "couple": "Baker, Andrew and Gress, Satit",
          "place": "5",
          "points": 10.0
        }
      ]
    },
    {
      "title": "AC-A Open Rhythm 3-Dance Challenge (C/R/SW)",
      "entries": [
        {
          "couple": "Colon and Torres",
          "place": "1",
          "points": 25.0
        },
        {
          "couple": "Bartlett, James and Jane, Catherine",
          "place": "2",
          "points": 17.5
        },
        {
          "couple": "Ward, Janice and Ward, Walter",
          "place": "3",
          "points": 12.5
        },
        {
          "couple": "Baker, Andrew and Gress, Satit",
          "place": "4",
          "points": 7.5
        }
      ]
    },
    {
      "title": "AC-JR Open Latin 3-Dance Challenge (C/S/R)",
      "entries": [
        {
          "couple": "McMains, Artiom and McMains, Tatiana",
          "place": "1",
          "points": 25
        }
      ]
    }
  ]
}