{
  "comp name": "Heritage Classic Ballroom Championships",
  "heats": [
    {
      "title": "<153>Professional Rising Star American Rhythm Competition (C/R/SW/B/M)",
      "entries": [
        {
          "couple": "Shipilov, Aleksei and Mitina, Julia",
          "place": "1",
          "points": 10.0
        },
        {
          "couple": "Ubillus, Kevin and Lareto, Milagros",
          "place": "2",
          "points": 8.0
        },
        {
          "couple": "Shiller, Ginny Ray and Shiller, Artem",
          "place": "3",
          "points": 6.5
        },
        {
          "couple": "Martinez, Juan and Bottinelli, Elayna",
          "place": "4",
          "points": 5.0
        },
        {
          "couple": "Chen, Jonathan and Simanekova, Juanita",
          "place": "5",
          "points": 4.0
        },
        {
          "couple": "Borges, Israel and Cardenas, Natalie",
          "place": "6",
          "points": 3.0
        },
        {
          "couple": "Dawson, Staz and Gonyea, Jacklyn",
          "place": "7",
          "points": 2.5
        }
      ]
    },
    {
      "title": "<154>Professional Rising Star Int'l Ballroom Competition (W/T/VW/FT/QS)",
      "entries": [
        {
          "couple": "Conte, Riccardo and Filippi, Eleonora",
          "place": "1",
          "points": 10.0
        },
        {
          "couple": "Kostianets, Valeriia and Kostianets, Slava",
          "place": "2",
          "points": 7.0
        },
        {
          "couple": "Izyumov, Sergey and Zaver, Oksana",
          "place": "3",
          "points": 5.0
        }
      ]
    },
    {
      "title": "<152>Professional Rising Star American Smooth Competition (W/T/FT/VW)",
      "entries": [
        {
          "couple": "Mora, Leo and Garced, Christina",
          "place": "1",
          "points": 20.0
        },
        {
          "couple": "Proper, William and Elliott, Jennifer",
          "place": "2",
          "points": 16.0
        },
        {
          "couple": "Guthrie, Trevor and Guthrie, Emily",
          "place": "3",
          "points": 13.0
        },
        {
          "couple": "Dawson, Staz and Gonyea, Jacklyn",
          "place": "4",
          "points": 10.0
        },
        {
          "couple": "Martinez, Juan and Bottinelli, Elayna",
          "place": "5",
          "points": 8.0
        },
        {
          "couple": "Stowell, Aaron and Hofreiter, Brie",
          "place": "6",
          "points": 6.0
        },
        {
          "couple": "Bryant, Jeffrey and Bracken, Rachel",
          "place": "Semis",
          "points": 2.4
        },
        {
          "couple": "Stockton, Andrew and Smith, Rachel",
          "place": "Semis",
          "points": 2.6
        }
      ]
    },
    {
      "title": "<155>Professional Rising Star Int'l Latin Competition (C/S/R/PD/J)",
      "entries": [
        {
          "couple": "Shipilov, Aleksei and Mitina, Julia",
          "place": "1",
          "points": 10.0
        },
        {
          "couple": "Elkin, Bozhidar and Dumanova, Elena",
          "place": "2",
          "points": 8.0
        },
        {
          "couple": "Fulvi, Daniele and Criscione, Veronica",
          "place": "3",
          "points": 6.5
        },
        {
          "couple": "Jenkins, Nora and Jenkins, Dylan",
          "place": "4",
          "points": 5.0
        }
      ]
    },
    {
      "title": "<151>Open Professional Cabaret/Exhibition Championship",
      "entries": [
        {
          "couple": "Jensen, Shannon and Jensen, Shane",
          "place": "1",
          "points": 20.0
        },
        {
          "couple": "Smith, Craig and Harvey, Andrey",
          "place": "2",
          "points": 16.0
        },
        {
          "couple": "Tuft, Travis and Tuft, Jaimee",
          "place": "3",
          "points": 13.0
        },
        {
          "couple": "Dombrowik, Douglas and Fox, Angel",
          "place": "4",
          "points": 10.0
        },
        {
          "couple": "Dawson, Staz and Gonyea, Jacklyn",
          "place": "5",
          "points": 8.0
        }
      ]
    },
    {
      "title": "<158>Open Professional Int'l Ballroom Championship(W/T/VW/FT/QS)",
      "entries": [
        {
          "couple": "Homm, Rudy and Kanevskaya, Katia",
          "place": "1",
          "points": 30.0
        },
        {
          "couple": "Shakhov, Vladislav and Popova, Ekaterina",
          "place": "2",
          "points": 24.0
        },
        {
          "couple": "Pappacena and Pappacena",
          "place": "3",
          "points": 19.5
        },
        {
          "couple": "Kazlauskas and Ilo",
          "place": "4",
          "points": 15.0
        },
        {
          "couple": "Tonizzo, Richard and Hansen, Claire",
          "place": "5",
          "points": 12.0
        },
        {
          "couple": "Conte, Riccardo and Filippi, Eleonora",
          "place": "6",
          "points": 9.0
        },
        {
          "couple": "Kostianets, Valeriia and Kostianets, Slava",
          "place": "Semis",
          "points": 7.5
        },
        {
          "couple": "Solomakha, Dmitriy and Sevillano, Gabriela",
          "place": "Semis",
          "points": 4.8
        }
      ]
    },
    {
      "title": "<157>Open Professional American Rhythm Championship(C/R/SW/B/M)",
      "entries": [
        {
          "couple": "Paramonov and Paramonov",
          "place": "1",
          "points": 30.0
        },
        {
          "couple": "Nikishkin, Dmitry and Shvets-Nikishkin, Olena",
          "place": "2",
          "points": 24.0
        },
        {
          "couple": "Jensen, Shannon and Jensen, Shane",
          "place": "3",
          "points": 19.5
        },
        {
          "couple": "Ubillus, Kevin and Lareto, Milagros",
          "place": "4",
          "points": 15.0
        },
        {
          "couple": "Shipilov, Aleksei and Mitina, Julia",
          "place": "5",
          "points": 12.0
        },
        {
          "couple": "Abdullin, Ilya and Jerjomina, Anastasija",
          "place": "6",
          "points": 9.0
        },
        {
          "couple": "Chen, Jonathan and Simanekova, Juanita",
          "place": "Semis",
          "points": 3.6
        },
        {
          "couple": "Dawson, Staz and Gonyea, Jacklyn",
          "place": "Semis",
          "points": 3.6
        },
        {
          "couple": "Don, Jang and Don, Adele",
          "place": "Semis",
          "points": 7.5
        },
        {
          "couple": "Shiller, Ginny Ray and Shiller, Artem",
          "place": "Semis",
          "points": 3.6
        }
      ]
    },
    {
      "title": "<156>Open Professional American Smooth Championship(W/T/FT/VW)",
      "entries": [
        {
          "couple": "Tuft, Travis and Tuft, Jaimee",
          "place": "1",
          "points": 40.0
        },
        {
          "couple": "Malkhasyan, Roman and Detkina, Galina",
          "place": "2",
          "points": 32.0
        },
        {
          "couple": "Kostianets, Valeriia and Kostianets, Slava",
          "place": "3",
          "points": 26.0
        },
        {
          "couple": "Pilipenchuk, Nikolai and Hudson, Sarika",
          "place": "4",
          "points": 20.0
        },
        {
          "couple": "Don, Jang and Don, Adele",
          "place": "5",
          "points": 16.0
        },
        {
          "couple": "Choi, Michael and Kleyman, Viktoriya",
          "place": "6",
          "points": 12.0
        },
        {
          "couple": "Mora, Leo and Garced, Christina",
          "place": "Semis",
          "points": 6.0
        },
        {
          "couple": "Guthrie, Trevor and Guthrie, Emily",
          "place": "Semis",
          "points": 4.8
        },
        {
          "couple": "Stowell, Aaron and Hofreiter, Brie",
          "place": "Semis",
          "points": 4.8
        },
        {
          "couple": "Rozenfeld, Evgenii and Shumakher, Maria",
          "place": "Semis",
          "points": 4.8
        },
        {
          "couple": "Bryant, Jeffrey and Bracken, Rachel",
          "place": "quarters",
          "points": 0.4
        },
        {
          "couple": "Dawson, Staz and Gonyea, Jacklyn",
          "place": "quarters",
          "points": 4.0
        },
        {
          "couple": "McElyea, Drew and Jones, Shannon",
          "place": "quarters",
          "points": 0.8
        }
      ]
    },
    {
      "title": "<159>Open Professional Int'l Latin Championship(C/S/R/PD/J)",
      "entries": [
        {
          "couple": "Mulyavka, Ivan and Rooba, Karin",
          "place": "1",
          "points": 30.0
        },
        {
          "couple": "Kudashev, Ivan and Sokolova, Ksenia",
          "place": "2",
          "points": 24.0
        },
        {
          "couple": "Shipilov and Mitina",
          "place": "3",
          "points": 19.5
        },
        {
          "couple": "Kazlauskas and Ilo",
          "place": "4",
          "points": 15.0
        },
        {
          "couple": "Alekseev, Aleksei and Derevleva, Ekaterina",
          "place": "5",
          "points": 12.0
        },
        {
          "couple": "Davies, Jake and Kalinina, Alyona",
          "place": "6",
          "points": 9.0
        },
        {
          "couple": "Elkin, Bozhidar and Dumanova, Elena",
          "place": "Semis",
          "points": 7.5
        },
        {
          "couple": "Jenkins, Nora and Jenkins, Dylan",
          "place": "Semis",
          "points": 3.6
        },
        {
          "couple": "Solomakha, Dmitriy and Sevillano, Gabriela",
          "place": "Semis",
          "points": 3.9
        }
      ]
    }
  ]
}