{
  "comp name": "Eastern United States Dancesport Championships",
  "heats": [
    {
      "number": 718,
      "title": "Youth Amateur 3-Dance Events Closed Bronze J1 Int'l Ballroom (W,T,Q)",
      "entries": [
        {
          "couple": "Grant, Austin and Astacio, Jacelys",
          "place": "1",
          "points": 6.0
        }
      ]
    },
    {
      "number": 718,
      "title": "Youth Amateur 3-Dance Events Closed Bronze mLP1 Int'l Ballroom (W,T,Q)",
      "entries": [
        {
          "couple": "Affonso, Christopher and Sanchez, Rosario",
          "place": "1",
          "points": 6.0
        }
      ]
    },
    {
      "number": 721,
      "title": "Amateur PreChamp 4-Dance Events mLJ1 Int'l Ballroom (W,T,F,Q)",
      "entries": [
        {
          "couple": "Kalenyuk, Oleksandr and Urman, Nicolette",
          "place": "1",
          "points": 9.0
        }
      ]
    },
    {
      "number": 721,
      "title": "Fordney Foundation Preteen Closed Syllabus Events P1 AM/AM Int'l Ballroom (W,T,VW,F,Q)",
      "entries": [
        {
          "couple": "Khelmer, Brian and Sherman, Emma",
          "place": "1",
          "points": 9.0
        }
      ]
    },
    {
      "number": 721,
      "title": "Youth Amateur 3-Dance Events Closed Bronze mLJ1 Int'l Ballroom (W,T,Q)",
      "entries": [
        {
          "couple": "Affonso, Christopher and Doricent, Isabel",
          "place": "1",
          "points": 6.0
        }
      ]
    },
    {
      "number": 726,
      "title": "Fordney Foundation Open Events J2 AM/AM Int'l Ballroom (W,T,VW,F,Q)",
      "entries": [
        {
          "couple": "Affonso, Christopher and Hatleberg, Holly",
          "place": "1",
          "points": 12.0
        }
      ]
    },
    {
      "number": 726,
      "title": "Fordney Foundation Open Events YH AM/AM Int'l Ballroom (W,T,VW,F,Q)",
      "entries": [
        {
          "couple": "Radionov, Sam and Kouznetsov, Sophia",
          "place": "1",
          "points": 18.0
        },
        {
          "couple": "Ginzburg, Joshua and Elkin, Sophia",
          "place": "2",
          "points": 12.0
        },
        {
          "couple": "Potagal, Michael and Potagal, Margaret",
          "place": "3",
          "points": 7.0
        }
      ]
    },
    {
      "number": 726,
      "title": "Fordney Foundation Preteen Closed Syllabus Events P2 AM/AM Int'l Ballroom (W,T,VW,F,Q)",
      "entries": [
        {
          "couple": "Khelmer, Brian and Sherman, Emma",
          "place": "1",
          "points": 9.0
        }
      ]
    },
    {
      "number": 726,
      "title": "Youth Amateur 5-Dance Events Champ mLJ1 Int'l Ballroom (W,T,VW,F,Q)",
      "entries": [
        {
          "couple": "Kalenyuk, Oleksandr and Sarram, Ava",
          "place": "1",
          "points": 12.0
        }
      ]
    },
    {
      "number": 729,
      "title": "Amateur PreChamp 4-Dance Events J2 Int'l Ballroom (W,T,F,Q)",
      "entries": [
        {
          "couple": "Affonso, Christopher and Hatleberg, Holly",
          "place": "1",
          "points": 9.0
        }
      ]
    },
    {
      "number": 809,
      "title": "Amateur Novice 3-Dance Events mLJ1 Int'l Latin (CC,S,R)",
      "entries": [
        {
          "couple": "Ginzburg, Joshua and Podolskaya, Sasha",
          "place": "1",
          "points": 3.0
        }
      ]
    },
    {
      "number": 809,
      "title": "Amateur PreChamp 4-Dance Events mLJ1 Int'l Latin (CC,S,R,J)",
      "entries": [
        {
          "couple": "Vasilenko, Nikita and Sarram, Ava",
          "place": "1",
          "points": 9.0
        }
      ]
    },
    {
      "number": 809,
      "title": "Youth Amateur 3-Dance Events Closed Bronze J1 Int'l Latin (CC,R,J)",
      "entries": [
        {
          "couple": "Grant, Austin and Astacio, Jacelys",
          "place": "1",
          "points": 6.0
        }
      ]
    },
    {
      "number": 809,
      "title": "Youth Amateur 3-Dance Events Closed Bronze P1 Int'l Latin (CC,R,J)",
      "entries": [
        {
          "couple": "Shi, Lucas and Zvenigorodsky, Sophia",
          "place": "1",
          "points": 7.5
        },
        {
          "couple": "Dew, Duncan and Chen, Angie",
          "place": "2",
          "points": 3.5
        }
      ]
    },
    {
      "number": 809,
      "title": "Youth Amateur 3-Dance Events Closed Bronze mLJ1 Int'l Latin (CC,R,J)",
      "entries": [
        {
          "couple": "Affonso, Christopher and Doricent, Isabel",
          "place": "1",
          "points": 6.0
        }
      ]
    },
    {
      "number": 812,
      "title": "Amateur Novice 3-Dance Events YH Int'l Latin (CC,S,R)",
      "entries": [
        {
          "couple": "Ulbrich, Devin and Malonova, Vika",
          "place": "1",
          "points": 3.0
        }
      ]
    },
    {
      "number": 815,
      "title": "Amateur Novice 3-Dance Events mLP2 Int'l Latin (CC,S,R)",
      "entries": [
        {
          "couple": "Ginzburg, Joshua and Yalli, Anna",
          "place": "1",
          "points": 3.0
        }
      ]
    },
    {
      "number": 815,
      "title": "Amateur PreChamp 4-Dance Events J2 Int'l Latin (CC,S,R,J)",
      "entries": [
        {
          "couple": "Affonso, Christopher and Hatleberg, Holly",
          "place": "1",
          "points": 9.0
        }
      ]
    },
    {
      "number": 815,
      "title": "Amateur PreChamp 4-Dance Events YH Int'l Latin (CC,S,R,J)",
      "entries": [
        {
          "couple": "Potagal, Michael and Potagal, Margaret",
          "place": "1",
          "points": 13.5
        },
        {
          "couple": "Goldovt, Raymond and Fridberg, Biana",
          "place": "2",
          "points": 9.0
        },
        {
          "couple": "Ulbrich, Devin and Malonova, Vika",
          "place": "3",
          "points": 5.25
        }
      ]
    },
    {
      "number": 815,
      "title": "Youth Amateur 4-Dance Events Closed Silver J1 Int'l Latin (CC,S,R,J)",
      "entries": [
        {
          "couple": "Kuo, Min Jae and Bunner, Katherine",
          "place": "1",
          "points": 9.0
        }
      ]
    },
    {
      "number": 816,
      "title": "Fordney Foundation Open Events J2 AM/AM Int'l Latin (CC,S,R,PD,J)",
      "entries": [
        {
          "couple": "Hayutt, Ethan and Jgenti, Anna",
          "place": "1",
          "points": 18.0
        },
        {
          "couple": "Nikitin, Marsel and Hoodyakova, Tonya",
          "place": "2",
          "points": 12.0
        },
        {
          "couple": "Affonso, Christopher and Hatleberg, Holly",
          "place": "3",
          "points": 7.0
        }
      ]
    },
    {
      "number": 816,
      "title": "Fordney Foundation Open Events YH AM/AM Int'l Latin (CC,S,R,PD,J)",
      "entries": [
        {
          "couple": "Ginzburg, Joshua and Elkin, Sophia",
          "place": "1",
          "points": 18.0
        },
        {
          "couple": "Potagal, Michael and Potagal, Margaret",
          "place": "2",
          "points": 12.0
        },
        {
          "couple": "Goldovt, Raymond and Fridberg, Biana",
          "place": "3",
          "points": 7.0
        }
      ]
    },
    {
      "number": 816,
      "title": "Fordney Foundation Preteen Closed Syllabus Events P1 AM/AM Int'l Latin (CC,S,R,PD,J)",
      "entries": [
        {
          "couple": "Khelmer, Brian and Sherman, Emma",
          "place": "1",
          "points": 9.0
        }
      ]
    },
    {
      "number": 818,
      "title": "Fordney Foundation Open Events J1 AM/AM Int'l Latin (CC,S,R,PD,J)",
      "entries": [
        {
          "couple": "Hayutt, Ethan and Jgenti, Anna",
          "place": "1",
          "points": 12.0
        }
      ]
    },
    {
      "number": 818,
      "title": "Fordney Foundation Preteen Closed Syllabus Events P2 AM/AM Int'l Latin (CC,S,R,PD,J)",
      "entries": [
        {
          "couple": "Khelmer, Brian and Sherman, Emma",
          "place": "1",
          "points": 9.0
        }
      ]
    },
    {
      "number": 818,
      "title": "Youth Amateur 5-Dance Events Champ mLJ1 Int'l Latin (CC,S,R,PD,J)",
      "entries": [
        {
          "couple": "Vasilenko, Nikita and Sarram, Ava",
          "place": "1",
          "points": 12.0
        }
      ]
    }
  ]
}